[{"process":"reference","subject":"add","data":{"reference":null,"group":"iblockSection","dbVersion":"480acdbefe3ba164b1ea62b234199ec1","id":false},"originalData":null,"name":"Reference fix","version":"480acdbefe3ba164b1ea62b234199ec1","owner":"RealServer"},{"process":"reference","subject":"add","data":{"reference":null,"group":"iblockSection","dbVersion":"480acdbefe3ba164b1ea62b234199ec1","id":false},"originalData":null,"name":"Reference fix","version":"480acdbefe3ba164b1ea62b234199ec1","owner":"RealServer"},{"process":"reference","subject":"add","data":{"reference":null,"group":"iblockSection","dbVersion":"480acdbefe3ba164b1ea62b234199ec1","id":false},"originalData":null,"name":"Reference fix","version":"480acdbefe3ba164b1ea62b234199ec1","owner":"RealServer"},{"process":"reference","subject":"add","data":{"reference":null,"group":"iblockSection","dbVersion":"480acdbefe3ba164b1ea62b234199ec1","id":false},"originalData":null,"name":"Reference fix","version":"480acdbefe3ba164b1ea62b234199ec1","owner":"RealServer"},{"process":"reference","subject":"add","data":{"reference":null,"group":"iblockSection","dbVersion":"480acdbefe3ba164b1ea62b234199ec1","id":false},"originalData":null,"name":"Reference fix","version":"480acdbefe3ba164b1ea62b234199ec1","owner":"RealServer"},{"process":"reference","subject":"add","data":{"reference":null,"group":"iblockSection","dbVersion":"480acdbefe3ba164b1ea62b234199ec1","id":false},"originalData":null,"name":"Reference fix","version":"480acdbefe3ba164b1ea62b234199ec1","owner":"RealServer"},{"process":"reference","subject":"add","data":{"reference":null,"group":"iblockSection","dbVersion":"480acdbefe3ba164b1ea62b234199ec1","id":false},"originalData":null,"name":"Reference fix","version":"480acdbefe3ba164b1ea62b234199ec1","owner":"RealServer"},{"process":"reference","subject":"add","data":{"reference":null,"group":"iblockSection","dbVersion":"480acdbefe3ba164b1ea62b234199ec1","id":false},"originalData":null,"name":"Reference fix","version":"480acdbefe3ba164b1ea62b234199ec1","owner":"RealServer"},{"process":"reference","subject":"add","data":{"reference":null,"group":"iblockSection","dbVersion":"480acdbefe3ba164b1ea62b234199ec1","id":false},"originalData":null,"name":"Reference fix","version":"480acdbefe3ba164b1ea62b234199ec1","owner":"RealServer"},{"process":"reference","subject":"add","data":{"reference":null,"group":"iblockSection","dbVersion":"480acdbefe3ba164b1ea62b234199ec1","id":false},"originalData":null,"name":"Reference fix","version":"480acdbefe3ba164b1ea62b234199ec1","owner":"RealServer"},{"process":"reference","subject":"add","data":{"reference":null,"group":"iblockSection","dbVersion":"480acdbefe3ba164b1ea62b234199ec1","id":false},"originalData":null,"name":"Reference fix","version":"480acdbefe3ba164b1ea62b234199ec1","owner":"RealServer"},{"process":"reference","subject":"add","data":{"reference":null,"group":"iblockSection","dbVersion":"480acdbefe3ba164b1ea62b234199ec1","id":false},"originalData":null,"name":"Reference fix","version":"480acdbefe3ba164b1ea62b234199ec1","owner":"RealServer"},{"process":"reference","subject":"add","data":{"reference":null,"group":"iblockSection","dbVersion":"480acdbefe3ba164b1ea62b234199ec1","id":false},"originalData":null,"name":"Reference fix","version":"480acdbefe3ba164b1ea62b234199ec1","owner":"RealServer"}]