[{"process":"WS\\Migrations\\Processes\\UpdateProcess","subject":"WS\\Migrations\\SubjectHandlers\\IblockSectionHandler","data":{"ID":"58","TIMESTAMP_X":{},"MODIFIED_BY":"1","DATE_CREATE":{},"CREATED_BY":"1","IBLOCK_ID":"4","IBLOCK_SECTION_ID":"14","ACTIVE":"Y","GLOBAL_ACTIVE":"Y","SORT":"100","NAME":"\u0416\u0415\u041d\u0421\u041a\u0410\u042f \u041e\u0414\u0415\u0416\u0414\u0410 \u041e\u041f\u0422\u041e\u041c (\u043e\u0441\u043d\u043e\u0432\u043d\u043e\u0439 \u0440\u0430\u0437\u0434\u0435\u043b)","PICTURE":"1119","LEFT_MARGIN":"2","RIGHT_MARGIN":"3","DEPTH_LEVEL":"2","DESCRIPTION":"","DESCRIPTION_TYPE":"text","SEARCHABLE_CONTENT":"\u0416\u0415\u041d\u0421\u041a\u0410\u042f \u041e\u0414\u0415\u0416\u0414\u0410 \u041e\u041f\u0422\u041e\u041c (\u041e\u0421\u041d\u041e\u0412\u041d\u041e\u0419 \u0420\u0410\u0417\u0414\u0415\u041b)\r\n","CODE":"zhenskaya-odezhda-optom-osnovnoy-razdel","XML_ID":null,"TMP_ID":null,"DETAIL_PICTURE":null,"SOCNET_GROUP_ID":null,"~reference":"6b9c755bea7ea8b95d28c7a84768c4f1"},"originalData":{"ID":"58","TIMESTAMP_X":{},"MODIFIED_BY":"1","DATE_CREATE":{},"CREATED_BY":"1","IBLOCK_ID":"4","IBLOCK_SECTION_ID":"14","ACTIVE":"Y","GLOBAL_ACTIVE":"Y","SORT":"500","NAME":"\u0416\u0415\u041d\u0421\u041a\u0410\u042f \u041e\u0414\u0415\u0416\u0414\u0410 \u041e\u041f\u0422\u041e\u041c (\u043e\u0441\u043d\u043e\u0432\u043d\u043e\u0439 \u0440\u0430\u0437\u0434\u0435\u043b)","PICTURE":"1119","LEFT_MARGIN":"8","RIGHT_MARGIN":"9","DEPTH_LEVEL":"2","DESCRIPTION":"","DESCRIPTION_TYPE":"text","SEARCHABLE_CONTENT":"\u0416\u0415\u041d\u0421\u041a\u0410\u042f \u041e\u0414\u0415\u0416\u0414\u0410 \u041e\u041f\u0422\u041e\u041c (\u041e\u0421\u041d\u041e\u0412\u041d\u041e\u0419 \u0420\u0410\u0417\u0414\u0415\u041b)\r\n","CODE":"zhenskaya-odezhda-optom-osnovnoy-razdel","XML_ID":null,"TMP_ID":null,"DETAIL_PICTURE":null,"SOCNET_GROUP_ID":null,"~reference":"6b9c755bea7ea8b95d28c7a84768c4f1"},"name":"\u0420\u0430\u0437\u0434\u0435\u043b \u0438\u043d\u0444\u043e\u0440\u043c\u0430\u0446\u0438\u043e\u043d\u043d\u043e\u0433\u043e \u0431\u043b\u043e\u043a\u0430. \u041e\u0431\u043d\u043e\u0432\u043b\u0435\u043d\u0438\u0435","version":"19ccf2e20fafdfd938538ef1aaf59a87","owner":"RealServer"}]